[
  {"ha": "sannu", "en": "hello"},
  {"ha": "barkatar safe", "en": "good morning"},
  {"ha": "barka da yamma", "en": "good evening"},
  {"ha": "na gode", "en": "thank you"},
  {"ha": "don Allah", "en": "please"},
  {"ha": "eh", "en": "yes"},
  {"ha": "a'a", "en": "no"},
  {"ha": "ruwa", "en": "water"},
  {"ha": "abinci", "en": "food"},
  {"ha": "gida", "en": "house"},
  {"ha": "kasuwa", "en": "market"},
  {"ha": "aboki", "en": "friend"},
  {"ha": "so", "en": "love"},
  {"ha": "uwargida", "en": "mother"},
  {"ha": "uba", "en": "father"},
  {"ha": "dan uwa", "en": "brother"},
  {"ha": "yar uwa", "en": "sister"},
  {"ha": "d'a", "en": "son"},
  {"ha": "'ya", "en": "daughter"},
  {"ha": "yaro", "en": "child"},
  {"ha": "mutum", "en": "man/person"},
  {"ha": "mace", "en": "woman"},
  {"ha": "yaro", "en": "boy"},
  {"ha": "yarinya", "en": "girl"},
  {"ha": "maktaba", "en": "school/library"},
  {"ha": "malami", "en": "teacher"},
  {"ha": "dalibi", "en": "student"},
  {"ha": "aiki", "en": "work"},
  {"ha": "asibiti", "en": "hospital"},
  {"ha": "kudi", "en": "money"},
  {"ha": "hanya", "en": "road"},
  {"ha": "mota", "en": "car"},
  {"ha": "bashi", "en": "bus"},
  {"ha": "jirgin kasa", "en": "train"},
  {"ha": "filin jirgi", "en": "airport"},
  {"ha": "shago", "en": "shop"},
  {"ha": "coci", "en": "church"},
  {"ha": "masallaci", "en": "mosque"},
  {"ha": "suna", "en": "name"},
  {"ha": "menene", "en": "what"},
  {"ha": "ina", "en": "where"},
  {"ha": "yaushe", "en": "when"},
  {"ha": "wane", "en": "who"},
  {"ha": "me yasa", "en": "why"},
  {"ha": "yadda", "en": "how"},
  {"ha": "ni", "en": "I"},
  {"ha": "kai/ke", "en": "you"},
  {"ha": "shi", "en": "he"},
  {"ha": "ita", "en": "she"},
  {"ha": "mu", "en": "we"},
  {"ha": "su", "en": "they"},
  {"ha": "ci", "en": "eat"},
  {"ha": "sha", "en": "drink"},
  {"ha": "barci", "en": "sleep"},
  {"ha": "tafi", "en": "go"},
  {"ha": "zo", "en": "come"},
  {"ha": "daina", "en": "stop"},
  {"ha": "taku", "en": "help"},
  {"ha": "yi hakuri", "en": "sorry"},
  {"ha": "barka da zuwa", "en": "welcome"},
  {"ha": "bandaki", "en": "bathroom"},
  {"ha": "waya", "en": "telephone"},
  {"ha": "likita", "en": "doctor"},
  {"ha": "yan sanda", "en": "police"},
  {"ha": "bude", "en": "open"},
  {"ha": "rufe", "en": "close"},
  {"ha": "zafi", "en": "hot"},
  {"ha": "sanyi", "en": "cold"},
  {"ha": "babba", "en": "big"},
  {"ha": "karami", "en": "small"},
  {"ha": "mai kyau", "en": "good"},
  {"ha": "mugun", "en": "bad"},
  {"ha": "kyawu", "en": "beautiful"},
  {"ha": "sabo", "en": "new"},
  {"ha": "tsoho", "en": "old"},
  {"ha": "hagu", "en": "left"},
  {"ha": "dama", "en": "right"},
  {"ha": "kai tsaye", "en": "straight"},
  {"ha": "kusa", "en": "near"},
  {"ha": "nisa", "en": "far"},
  {"ha": "yau", "en": "today"},
  {"ha": "gobe", "en": "tomorrow"},
  {"ha": "jibi", "en": "yesterday"},
  {"ha": "safe", "en": "morning"},
  {"ha": "yamma", "en": "evening"},
  {"ha": "dare", "en": "night"},
  {"ha": "yanzu", "en": "now"},
  {"ha": "bayan haka", "en": "later"},
  {"ha": "don Allah ka taimake ni", "en": "please help"},
  {"ha": "nawa ne", "en": "how much"},
  {"ha": "Ina son ku", "en": "I love you"},
  {"ha": "sai anjima", "en": "goodbye"}
]
